Metadata-Version: 2.1
Name: odoo13-addon-shopfloor
Version: 13.0.4.13.1
Summary: manage warehouse operations with barcode scanners
Home-page: https://github.com/OCA/wms
Author: Camptocamp, BCIM, Akretion, Odoo Community Association (OCA)
Author-email: support@odoo-community.org
License: AGPL-3
Platform: UNKNOWN
Classifier: Programming Language :: Python
Classifier: Framework :: Odoo
Classifier: Framework :: Odoo :: 13.0
Classifier: License :: OSI Approved :: GNU Affero General Public License v3
Classifier: Development Status :: 3 - Alpha
Requires-Python: >=3.5
Requires-Dist: odoo13-addon-auth-api-key
Requires-Dist: odoo13-addon-base-jsonify
Requires-Dist: odoo13-addon-base-rest
Requires-Dist: odoo13-addon-product-manufacturer
Requires-Dist: odoo13-addon-product-packaging-type
Requires-Dist: odoo13-addon-shopfloor-base
Requires-Dist: odoo13-addon-stock-helper
Requires-Dist: odoo13-addon-stock-picking-completion-info
Requires-Dist: odoo13-addon-stock-picking-delivery-link
Requires-Dist: odoo13-addon-stock-quant-package-dimension
Requires-Dist: odoo13-addon-stock-quant-package-product-packaging
Requires-Dist: odoo13-addon-stock-storage-type
Requires-Dist: odoo (<13.1dev,>=13.0a)
